{
  "login": "/auth",
  "signUp": "/auth/signup",
  "passwordReset": "/auth/reset-password",
  "lock": "/auth/lock",
  "dashboard": "/dashboard",
  "applet": "/dashboard/:id",
  "appletRespondents": "/dashboard/:id/respondents",
  "appletRespondentData": "/dashboard/:id/respondents/:respondentId/data",
  "appletRespondentDataSummary": "/dashboard/:id/respondents/:respondentId/data/summary",
  "appletRespondentDataReview": "/dashboard/:id/respondents/:respondentId/data/review",
  "appletManagers": "/dashboard/:id/managers",
  "appletSchedule": "/dashboard/:id/schedule",
  "appletSettings": "/dashboard/:id/settings",
  "appletSettingsItem": "/dashboard/:id/settings/:settingItem",
  "appletAddUser": "/dashboard/:id/add-user",
  "builder": "/builder",
  "newApplet": "/builder/new-applet",
  "newAppletAbout": "/builder/new-applet/about",
  "newAppletActivities": "/builder/new-applet/activities",
  "newAppletNewActivity": "/builder/new-applet/activities/new-activity",
  "newAppletNewActivityAbout": "/builder/new-applet/activities/new-activity/about",
  "newAppletNewActivityItems": "/builder/new-applet/activities/new-activity/items",
  "newAppletNewActivityItemFlow": "/builder/new-applet/activities/new-activity/item-flow",
  "newAppletNewActivitySettings": "/builder/new-applet/activities/new-activity/settings",
  "newAppletActivityFlow": "/builder/new-applet/activity-flow",
  "newAppletNewActivityFlow": "/builder/new-applet/activity-flow/new-activity-flow",
  "newAppletNewActivityFlowAbout": "/builder/new-applet/activity-flow/new-activity-flow/about",
  "newAppletNewActivityFlowBuilder": "/builder/new-applet/activity-flow/new-activity-flow/builder",
  "newAppletSettings": "/builder/new-applet/settings",
  "newAppletSettingsItem": "/builder/new-applet/settings/:settingItem",
  "library": "/library",
  "libraryAppletDetails": "/library/:id",
  "libraryCart": "/library/cart"
}
